pystark/serialize.py
pystark/pystark.cpython-310-x86_64-linux-gnu.so
pystark/__init__.py
stark_sim.libs/libgomp-a34b3233.so.1.0.0
stark_sim-0.0.2.dist-info/WHEEL
stark_sim-0.0.2.dist-info/RECORD
stark_sim-0.0.2.dist-info/METADATA
