Metadata-Version: 2.1
Name: stark-sim
Version: 0.0.2
Summary: Stark is a C++ and Python simulation _platform_ that provides easy access to state-of-the-art methods to robustly solve challenging simulations of rigid and/or deformable objects in a strongly coupled manner.
Author-Email: =?utf-8?q?Jos=C3=A9_Antonio_Fern=C3=A1ndez-Fern=C3=A1ndez?= <fernandez@cs.rwth-aachen.de>, =?utf-8?q?Fabian_L=C3=B6schner?= <loeschner@cs.rwth-aachen.de>, Stefan Rhys Jeske <contact@srjeske.de>
Classifier: License :: OSI Approved :: Apache Software License
Project-URL: Homepage, https://github.com/InteractiveComputerGraphics/stark
Requires-Python: >=3.8
Requires-Dist: numpy>=1.23.0
